dwave/inspector/__init__.py
dwave/inspector/adapters.py
dwave/inspector/config.py
dwave/inspector/package_info.py
dwave/inspector/proxies.py
dwave/inspector/server.py
dwave/inspector/storage.py
dwave/inspector/utils.py
dwave/inspector/viewers.py
dwave_inspector-0.5.4.dist-info/licenses/LICENSE
dwave_inspector-0.5.4.dist-info/METADATA
dwave_inspector-0.5.4.dist-info/WHEEL
dwave_inspector-0.5.4.dist-info/entry_points.txt
dwave_inspector-0.5.4.dist-info/top_level.txt
dwave_inspector-0.5.4.dist-info/RECORD
