Metadata-Version: 2.4
Name: dwave-inspector
Version: 0.5.4
Summary: D-Wave Problem Inspector tool
Home-page: https://github.com/dwavesystems/dwave-inspector
Author: D-Wave Systems Inc.
Author-email: radomir@dwavesys.com
License: Apache 2.0
Classifier: License :: OSI Approved :: Apache Software License
Classifier: Operating System :: OS Independent
Classifier: Development Status :: 3 - Alpha
Classifier: Programming Language :: Python :: 3
Classifier: Programming Language :: Python :: 3.9
Classifier: Programming Language :: Python :: 3.10
Classifier: Programming Language :: Python :: 3.11
Classifier: Programming Language :: Python :: 3.12
Classifier: Programming Language :: Python :: 3.13
Requires-Python: >=3.9
License-File: LICENSE
Requires-Dist: dimod>=0.10.0
Requires-Dist: dwave-system>=1.3.0
Requires-Dist: dwave-cloud-client<0.14.0,>=0.12.0
Requires-Dist: Flask<4,>=2.2
Requires-Dist: numpy
Requires-Dist: orjson>=3.10.0
Provides-Extra: test
Requires-Dist: coverage>=7.0.0; extra == "test"
Requires-Dist: vcrpy; extra == "test"
Requires-Dist: importlib-metadata>=4.8; python_version < "3.10"
Dynamic: author
Dynamic: author-email
Dynamic: classifier
Dynamic: description
Dynamic: home-page
Dynamic: license
Dynamic: license-file
Dynamic: provides-extra
Dynamic: requires-dist
Dynamic: requires-python
Dynamic: summary
